ckanext_baepublisher-0.5-py3.7-nspkg.pth
ckanext/baepublisher/plugin.py
ckanext/baepublisher/store_connector.py
ckanext/baepublisher/assets/logo-ckan.png
ckanext/baepublisher/controllers/__init__.py
ckanext/baepublisher/controllers/ui_controller.py
ckanext/baepublisher/fanstatic/image_upload.js
ckanext/baepublisher/templates/package/edit_base.html
ckanext/baepublisher/templates/package/publish.html
ckanext/baepublisher/templates/package/snippets/storepublisher_publish_form.html
ckanext_baepublisher-0.5.dist-info/METADATA
ckanext_baepublisher-0.5.dist-info/RECORD
ckanext_baepublisher-0.5.dist-info/WHEEL
ckanext_baepublisher-0.5.dist-info/entry_points.txt
ckanext_baepublisher-0.5.dist-info/namespace_packages.txt
ckanext_baepublisher-0.5.dist-info/top_level.txt
