Metadata-Version: 2.1
Name: ckanext-baepublisher
Version: 0.5
Summary: CKAN extension allowing users to publish datasets in the FIWARE Business API Ecosystem as offerings in an easy way.
Home-page: https://github.com/FIWARE-TMForum/ckanext-baepublisher
Author: Aitor Magan, Francisco de la Vega
Author-email: fdelavega@conwet.com
License: AGPLv3+
Keywords: CKAN FIWARE BAE TM Forum Business API Ecosystem monetization
Platform: UNKNOWN
Classifier: Development Status :: 5 - Production/Stable
Classifier: License :: OSI Approved :: GNU Affero General Public License v3 or later (AGPLv3+)
Classifier: Operating System :: OS Independent
Classifier: Programming Language :: Python :: 2
Classifier: Programming Language :: Python :: 2.7
Requires-Dist: ckanext-oauth2 (>=0.4.0)
Requires-Dist: ckanext-privatedatasets (>=0.4)
